{"_type":"export","__export_format":4,"__export_date":"2023-09-14T20:33:00.664Z","__export_source":"insomnia.desktop.app:v2023.5.8","resources":[{"_id":"req_251985089a7f450ea517493000ebc205","parentId":"fld_75a570a0331c4ffb885741b4c2cb2eaa","modified":1694704469014,"created":1694704382201,"url":"{{host}}/videos/{% response 'body', 'req_9b793b64a5574b689ec4e45c5f6dbe60', 'b64::JC5pZA==::46b', 'never', 60 %}/generate","name":"Generate from prompt","description":"","method":"POST","body":{"mimeType":"application/json","text":"{\n\t\"temperature\": 0.5,\n\t\"prompt\": \"Seu papel é gerar três títulos para um vídeo do YouTube.\\n\\nAbaixo você receberá uma transcrição desse vídeo, use essa transcrição para gerar os títulos.\\nAbaixo você também receberá uma lista de títulos, use essa lista como referência para os títulos a serem gerados.\\n\\nOs títulos devem ter no máximo 60 caracteres.\\nOs títulos devem ser chamativos e atrativos para maximizar os cliques.\\n\\nRetorne APENAS os três títulos em formato de lista como no exemplo abaixo:\\n'''\\n- Título 1\\n- Título 2\\n- Título 3\\n'''\\n\\nTranscrição:\\n'''\\n{transcription}\\n'''\"\n}"},"parameters":[],"headers":[{"name":"Content-Type","value":"application/json"},{"name":"User-Agent","value":"insomnia/2023.5.8"}],"authentication":{},"metaSortKey":-1694704382201,"isPrivate":false,"settingStoreCookies":true,"settingSendCookies":true,"settingDisableRenderRequestBody":false,"settingEncodeUrl":true,"settingRebuildPath":true,"settingFollowRedirects":"global","_type":"request"},{"_id":"fld_75a570a0331c4ffb885741b4c2cb2eaa","parentId":"wrk_cb94040c0a91400baa49e75c0319daa8","modified":1694702224102,"created":1694702224102,"name":"Videos","description":"","environment":{},"environmentPropertyOrder":null,"metaSortKey":-1694702224103,"_type":"request_group"},{"_id":"wrk_cb94040c0a91400baa49e75c0319daa8","parentId":null,"modified":1694723545142,"created":1694701400069,"name":"Video Describer","description":"","scope":"collection","_type":"workspace"},{"_id":"req_c0551c6ca9934f45b1633e9cca3e3e59","parentId":"fld_75a570a0331c4ffb885741b4c2cb2eaa","modified":1694705725745,"created":1694702226629,"url":"{{host}}/videos/{% response 'body', 'req_9b793b64a5574b689ec4e45c5f6dbe60', 'b64::JC5pZA==::46b', 'never', 60 %}/transcription","name":"Transcription","description":"","method":"POST","body":{"mimeType":"application/json","text":"{\n\t\"prompt\": \"skate, skateboarding\"\n}"},"parameters":[],"headers":[{"name":"Content-Type","value":"application/json"},{"name":"User-Agent","value":"insomnia/2023.5.8"}],"authentication":{},"metaSortKey":-1694702226629,"isPrivate":false,"settingStoreCookies":true,"settingSendCookies":true,"settingDisableRenderRequestBody":false,"settingEncodeUrl":true,"settingRebuildPath":true,"settingFollowRedirects":"global","_type":"request"},{"_id":"req_9b793b64a5574b689ec4e45c5f6dbe60","parentId":"fld_715ae96cc6e94d788eb2a225bc546082","modified":1694723570532,"created":1694701581553,"url":"{{host}}/upload","name":"Upload MP3","description":"","method":"POST","body":{"mimeType":"multipart/form-data","params":[{"id":"pair_8859b43be38e4b0a9f60de8a9e025c9a","name":"file","value":"","description":"","type":"file"}]},"parameters":[],"headers":[{"name":"Content-Type","value":"multipart/form-data"},{"name":"User-Agent","value":"insomnia/2023.5.8"}],"authentication":{},"metaSortKey":-1694701581553,"isPrivate":false,"settingStoreCookies":true,"settingSendCookies":true,"settingDisableRenderRequestBody":false,"settingEncodeUrl":true,"settingRebuildPath":true,"settingFollowRedirects":"global","_type":"request"},{"_id":"fld_715ae96cc6e94d788eb2a225bc546082","parentId":"wrk_cb94040c0a91400baa49e75c0319daa8","modified":1694701577918,"created":1694701577918,"name":"Uploads","description":"","environment":{},"environmentPropertyOrder":null,"metaSortKey":-1694701577918,"_type":"request_group"},{"_id":"req_929ac168c80c476b8b51c9d5c2008471","parentId":"fld_0b1a33bf10434783bef294688ea29a9b","modified":1694701510000,"created":1694701430859,"url":"{{host}}/prompts","name":"Index","description":"","method":"GET","body":{},"parameters":[],"headers":[{"name":"User-Agent","value":"insomnia/2023.5.8"}],"authentication":{},"metaSortKey":-1694701463815,"isPrivate":false,"settingStoreCookies":true,"settingSendCookies":true,"settingDisableRenderRequestBody":false,"settingEncodeUrl":true,"settingRebuildPath":true,"settingFollowRedirects":"global","_type":"request"},{"_id":"fld_0b1a33bf10434783bef294688ea29a9b","parentId":"wrk_cb94040c0a91400baa49e75c0319daa8","modified":1694701459989,"created":1694701459989,"name":"Prompts","description":"","environment":{},"environmentPropertyOrder":null,"metaSortKey":-1694701459989,"_type":"request_group"},{"_id":"env_e8c0ff51baee2aadac25c3e6f385dd627aacfca3","parentId":"wrk_cb94040c0a91400baa49e75c0319daa8","modified":1694701400074,"created":1694701400074,"name":"Base Environment","data":{},"dataPropertyOrder":null,"color":null,"isPrivate":false,"metaSortKey":1694701400074,"_type":"environment"},{"_id":"jar_e8c0ff51baee2aadac25c3e6f385dd627aacfca3","parentId":"wrk_cb94040c0a91400baa49e75c0319daa8","modified":1694701400076,"created":1694701400076,"name":"Default Jar","cookies":[],"_type":"cookie_jar"},{"_id":"env_d80bada9aa204c9d91b2c1f0b4aa0a91","parentId":"env_e8c0ff51baee2aadac25c3e6f385dd627aacfca3","modified":1694701501384,"created":1694701471900,"name":"dev","data":{"host":"http://127.0.0.1:3333"},"dataPropertyOrder":{"&":["host"]},"color":null,"isPrivate":false,"metaSortKey":1694701471900,"_type":"environment"}]}